abstochkin/__init__.py
abstochkin/_simulation_methods.py
abstochkin/agentstatedata.py
abstochkin/base.py
abstochkin/de_calcs.py
abstochkin/graphing.py
abstochkin/het_calcs.py
abstochkin/logging_config.py
abstochkin/process.py
abstochkin/simulation.py
abstochkin/utils.py
abstochkin-0.3.1.dist-info/METADATA
abstochkin-0.3.1.dist-info/WHEEL
abstochkin-0.3.1.dist-info/licenses/LICENSE
abstochkin-0.3.1.dist-info/RECORD
