Metadata-Version: 2.4
Name: abstochkin
Version: 0.3.1
Summary: Agent-based Stochastic Kinetics: A method for simulating the dynamics of heterogeneous populations.
Project-URL: Homepage, https://github.com/alexplaka/AbStochKin
Project-URL: Documentation, https://alexplaka.github.io/AbStochKin
Project-URL: Issues, https://github.com/alexplaka/AbStochKin/issues
Author-email: Alex Plakantonakis <alex.plaka@alumni.princeton.edu>
Maintainer-email: Alex Plakantonakis <alex.plaka@alumni.princeton.edu>
License:                     GNU GENERAL PUBLIC LICENSE
License-File: LICENSE
Classifier: Development Status :: 3 - Alpha
Classifier: License :: OSI Approved :: GNU General Public License v3 or later (GPLv3+)
Classifier: Operating System :: OS Independent
Classifier: Programming Language :: Python :: 3 :: Only
Classifier: Programming Language :: Python :: 3.12
Classifier: Programming Language :: Python :: 3.13
Classifier: Programming Language :: Python :: 3.14
Classifier: Topic :: Scientific/Engineering
Requires-Python: >=3.12
Requires-Dist: matplotlib>=3.5
Requires-Dist: numpy>=1.24
Requires-Dist: plotly>=5.24
Requires-Dist: scipy>=1.10
Requires-Dist: sympy>=1.10
Requires-Dist: tqdm>=4.66
Provides-Extra: docs
Requires-Dist: myst-parser>=2.0; extra == 'docs'
Requires-Dist: pdoc>=15; extra == 'docs'
Requires-Dist: sphinx>=7.0; extra == 'docs'
Provides-Extra: plotly
Requires-Dist: kaleido; extra == 'plotly'
